pgflux/__init__.py
pgflux/cli.py
pgflux/core.py
pgflux/enums.py
pgflux/exc.py
pgflux/influx.py
pgflux/output/__init__.py
pgflux/output/http.py
pgflux/output/interface.py
pgflux/output/stream.py
pgflux/queries/cluster/connections/0.0.sql
pgflux/queries/cluster/connections/10.0.sql
pgflux/queries/cluster/connections/9.2.sql
pgflux/queries/cluster/global_sizes/0.0.sql
pgflux/queries/cluster/locks/0.0.sql
pgflux/queries/cluster/query_ages/0.0.sql
pgflux/queries/cluster/query_ages/9.2.sql
pgflux/queries/cluster/temp_bytes/0.0.sql
pgflux/queries/cluster/transactions/0.0.sql
pgflux/queries/db/disk_io/0.0.sql
pgflux/queries/db/index_io/0.0.sql
pgflux/queries/db/row_access/0.0.sql
pgflux/queries/db/scan_types/0.0.sql
pgflux/queries/db/sequences_io/0.0.sql
pgflux/queries/db/size_by_db/0.0.sql
pgflux/queries/db/size_by_table/0.0.sql
pgflux/queries/db_size/0.0.sql
pgflux-1.1.0.dist-info/LICENSE
pgflux-1.1.0.dist-info/METADATA
pgflux-1.1.0.dist-info/WHEEL
pgflux-1.1.0.dist-info/entry_points.txt
pgflux-1.1.0.dist-info/top_level.txt
pgflux-1.1.0.dist-info/RECORD
