Metadata-Version: 2.1
Name: pgflux
Version: 1.1.0
Summary: Script for monitoring PostgreSQL databases with InfluxDB
Author: Michel Albert
Author-email: michel.albert@post.lu
License: MIT
Project-URL: Source, https://github.com/post-luxembourg/pgflux
Project-URL: Tracker, https://github.com/post-luxembourg/pgflux/issues
Project-URL: Documentation, https://post-luxembourg.github.io/pgflux/
Keywords: influxdb,postgresql
Platform: UNKNOWN
Classifier: Development Status :: 5 - Production/Stable
Classifier: Environment :: Console
Classifier: Environment :: Other Environment
Classifier: Intended Audience :: Developers
Classifier: Intended Audience :: Information Technology
Classifier: Intended Audience :: System Administrators
Classifier: License :: OSI Approved :: MIT License
Classifier: Operating System :: OS Independent
Classifier: Programming Language :: Python :: 3
Classifier: Programming Language :: Python :: 3.6
Classifier: Programming Language :: Python :: 3 :: Only
Classifier: Topic :: System :: Monitoring
Classifier: Typing :: Typed
License-File: LICENSE
Requires-Dist: psycopg2-binary
Requires-Dist: python-dotenv
Requires-Dist: importlib-metadata ; python_version < "3.8"
Provides-Extra: dev
Requires-Dist: black ; extra == 'dev'
Requires-Dist: pylint ; extra == 'dev'
Requires-Dist: sphinx ; extra == 'dev'
Requires-Dist: sphinx-rtd-theme ; extra == 'dev'
Provides-Extra: test
Requires-Dist: pytest ; extra == 'test'
Requires-Dist: pytest-cache ; extra == 'test'
Requires-Dist: pytest-coverage ; extra == 'test'
